vollsegzarr/CARE.py
vollsegzarr/CellPose.py
vollsegzarr/MASKUNET.py
vollsegzarr/OptimizeThreshold.py
vollsegzarr/PredictTiledLoader.py
vollsegzarr/Projection3D.py
vollsegzarr/ProjectionUpsampling3D.py
vollsegzarr/SimplePatches.py
vollsegzarr/SmartNucleiPatches.py
vollsegzarr/SmartPatches.py
vollsegzarr/SmartSeeds2D.py
vollsegzarr/SmartSeeds3D.py
vollsegzarr/StarDist2D.py
vollsegzarr/StarDist3D.py
vollsegzarr/Tiles.py
vollsegzarr/Tiles_3D.py
vollsegzarr/TrainTiledLoader.py
vollsegzarr/UNET.py
vollsegzarr/__init__.py
vollsegzarr/_version.py
vollsegzarr/chunked_segmentation.py
vollsegzarr/get_data.py
vollsegzarr/inference.py
vollsegzarr/inrimage.py
vollsegzarr/matching.py
vollsegzarr/nmslabel.py
vollsegzarr/pretrained.py
vollsegzarr/seedpool.py
vollsegzarr/spatial_image.py
vollsegzarr/unetstarmask.py
vollsegzarr/utils.py
vollsegzarr/zarr_io.py
vollsegzarr/_tests/__init__.py
vollsegzarr-0.0.3.dist-info/licenses/LICENSE
vollsegzarr-0.0.3.dist-info/METADATA
vollsegzarr-0.0.3.dist-info/WHEEL
vollsegzarr-0.0.3.dist-info/entry_points.txt
vollsegzarr-0.0.3.dist-info/top_level.txt
vollsegzarr-0.0.3.dist-info/RECORD
